{
  "lastChecks": {
    "system_status": 1741770600,
    "project_progress": 1741770600,
    "learning_output": 1741770600,
    "automation_tasks": 1741770600
  },
  "checkHistory": [
    {
      "timestamp": 1741767000,
      "time": "2026-03-12 04:10:00",
      "checksPerformed": [
        "openclaw_gateway_status",
        "memory_disk_usage",
        "network_connectivity",
        "techart_collector_status",
        "idea_generator_status"
      ],
      "outputsCreated": [
        "2026-03-12-openclaw-architecture.md",
        "AGENTS.md更新(心跳检查指南)"
      ],
      "learningTopics": [
        "OpenClaw架构分析",
        "系统监控方法",
        "技能系统设计"
      ],
      "problemsAnalyzed": [
        "OpenClaw CLI路径配置问题"
      ]
    },
    {
      "timestamp": 1741770600,
      "time": "2026-03-12 05:10:00",
      "checksPerformed": [
        "openclaw_gateway_quick_check",
        "memory_usage_check"
      ],
      "outputsCreated": [
        "2026-03-12-python-async-advanced.md"
      ],
      "learningTopics": [
        "Python异步上下文管理器",
        "异步迭代器和生成器",
        "任务组模式",
        "异步队列模式",
        "异步锁和信号量",
        "异步超时和取消",
        "异步错误处理",
        "性能优化技巧"
      ],
      "problemsAnalyzed": [
        "异步编程常见陷阱分析"
      ],
      "note": "非标准检查时间点(5:10)，执行轻量级检查和学习产出"
    },
    {
      "timestamp": 1741774200,
      "time": "2026-03-12 06:10:00",
      "checksPerformed": [
        "openclaw_gateway_status",
        "memory_disk_usage",
        "network_connectivity",
        "techart_collector_status",
        "idea_generator_check"
      ],
      "outputsCreated": [
        "2026-03-12-docker-advanced.md",
        "AGENTS.md更新(Docker最佳实践)"
      ],
      "learningTopics": [
        "Docker多阶段构建优化",
        "容器安全最佳实践",
        "性能优化技巧",
        "网络配置优化",
        "存储卷管理",
        "健康检查配置",
        "资源限制设置",
        "日志管理策略",
        "监控和调试工具",
        "CI/CD集成"
      ],
      "problemsAnalyzed": [
        "Docker生产环境常见问题分析"
      ],
      "note": "标准检查时间点(6:00)，执行完整检查"
    },
    {
      "timestamp": 1741777800,
      "time": "2026-03-12 08:10:00",
      "checksPerformed": [
        "openclaw_gateway_quick_check",
        "memory_usage_check"
      ],
      "outputsCreated": [
        "2026-03-12-kubernetes-basics.md"
      ],
      "learningTopics": [
        "Kubernetes架构概述",
        "核心对象概念(Pod/Deployment/Service)",
        "配置管理(ConfigMap/Secret)",
        "存储管理(PV/PVC)",
        "网络概念和Ingress",
        "工作负载控制器",
        "命名空间和资源配额",
        "健康检查和自愈机制",
        "常用kubectl命令"
      ],
      "problemsAnalyzed": [
        "容器编排平台学习路径分析"
      ],
      "note": "非标准检查时间点(8:10)，执行轻量级检查和学习产出"
    }
  ],
  "metrics": {
    "totalHeartbeats": 4,
    "totalOutputs": 6,
    "totalLearningTopics": 30,
    "totalProblemsAnalyzed": 4,
    "lastSuccessfulCheck": "2026-03-12 08:10:00",
    "averageOutputsPerHeartbeat": 1.5,
    "averageLearningTopicsPerHeartbeat": 7.5,
    "standardCheckPoints": ["04:10", "06:10"],
    "nonStandardChecks": ["05:10", "08:10"],
    "knowledgeDomains": ["OpenClaw架构", "Python异步编程", "Docker容器化", "Kubernetes基础"]
  }
}